<?xml version="1.0" encoding="utf-8"?>
<map
  p1:version=""
  p2:title="" xmlns:p2="livingroom" xmlns:p1="0.1">
  <nodes>
    <node>
      <index>0</index>
      <x>196</x>
      <y>233</y>
      <animMode>Walking</animMode>
    </node>
    <node>
      <index>1</index>
      <x>551</x>
      <y>234</y>
      <animMode>Walking</animMode>
    </node>
    <node>
      <index>2</index>
      <x>632</x>
      <y>212</y>
      <animMode>Jumping</animMode>
    </node>
    <node>
      <index>3</index>
      <x>710</x>
      <y>275</y>
      <animMode>Jumping</animMode>
    </node>
    <node>
      <index>4</index>
      <x>1111</x>
      <y>308</y>
      <animMode>Walking</animMode>
    </node>
    <node>
      <index>5</index>
      <x>714</x>
      <y>289</y>
      <animMode>Walking</animMode>
    </node>
    <node>
      <index>6</index>
      <x>612</x>
      <y>269</y>
      <animMode>Jumping</animMode>
    </node>
    <node>
      <index>7</index>
      <x>545</x>
      <y>310</y>
      <animMode>Jumping</animMode>
    </node>
    <node>
      <index>8</index>
      <x>200</x>
      <y>313</y>
      <animMode>Walking</animMode>
    </node>
    <node>
      <index>9</index>
      <x>521</x>
      <y>314</y>
      <animMode>Walking</animMode>
    </node>
    <node>
      <index>10</index>
      <x>625</x>
      <y>253</y>
      <animMode>Jumping</animMode>
    </node>
    <node>
      <index>11</index>
      <x>767</x>
      <y>295</y>
      <animMode>Jumping</animMode>
    </node>
    <node>
      <index>12</index>
      <x>1126</x>
      <y>298</y>
      <animMode>Walking</animMode>
    </node>
    <node>
      <index>13</index>
      <x>721</x>
      <y>298</y>
      <animMode>Walking</animMode>
    </node>
    <node>
      <index>14</index>
      <x>629</x>
      <y>232</y>
      <animMode>Jumping</animMode>
    </node>
    <node>
      <index>15</index>
      <x>552</x>
      <y>196</y>
      <animMode>Jumping</animMode>
    </node>
    <node>
      <index>16</index>
      <x>480</x>
      <y>232</y>
      <animMode>Jumping</animMode>
    </node>
    <node>
      <index>17</index>
      <x>196</x>
      <y>233</y>
      <animMode>Walking</animMode>
    </node>
    <node>
      <index>18</index>
      <x>480</x>
      <y>232</y>
      <animMode>Walking</animMode>
    </node>
  </nodes>
</map>